sillysort/__init__.py
sillysort/cli.py
sillysort/sillysort.py
sillysort-0.2.0.dist-info/DESCRIPTION.rst
sillysort-0.2.0.dist-info/METADATA
sillysort-0.2.0.dist-info/RECORD
sillysort-0.2.0.dist-info/WHEEL
sillysort-0.2.0.dist-info/entry_points.txt
sillysort-0.2.0.dist-info/metadata.json
sillysort-0.2.0.dist-info/top_level.txt
