Metadata-Version: 2.0
Name: sillysort
Version: 0.2.0
Summary: Sort things in a silly way.
Home-page: https://github.com/renanEccel/sillysort
Author: Renan Artur Lopes Eccel
Author-email: renan.eccel@gmail.com
License: MIT license
Keywords: sillysort
Platform: UNKNOWN
Classifier: Development Status :: 2 - Pre-Alpha
Classifier: Intended Audience :: Developers
Classifier: License :: OSI Approved :: MIT License
Classifier: Natural Language :: English
Classifier: Programming Language :: Python :: 2
Classifier: Programming Language :: Python :: 2.7
Classifier: Programming Language :: Python :: 3
Classifier: Programming Language :: Python :: 3.4
Classifier: Programming Language :: Python :: 3.5
Classifier: Programming Language :: Python :: 3.6
Requires-Dist: Click (>=6.0)
